graphene_t2/__init__.py
graphene_t2/fields.py
graphene_t2/options.py
graphene_t2/types.py
graphene_t2/utils.py
graphene_t2/features/__init__.py
graphene_t2/features/changes.py
graphene_t2/features/model_info.py
graphene_t2/features/ordering.py
graphene_t2/features/required.py
graphene_t2-0.4.0.dist-info/LICENSE
graphene_t2-0.4.0.dist-info/METADATA
graphene_t2-0.4.0.dist-info/WHEEL
graphene_t2-0.4.0.dist-info/top_level.txt
graphene_t2-0.4.0.dist-info/RECORD
