Metadata-Version: 2.1
Name: graphene-t2
Version: 0.4.0
Summary: An extension for graphene
Home-page: https://github.com/rustemg/graphene-t2
Author: Röstäm Gazizov
Author-email: gazizov@tn.ru
License: MIT
Keywords: api graphql graphene
Platform: UNKNOWN
Classifier: Development Status :: 3 - Alpha
Classifier: Intended Audience :: Developers
Classifier: Topic :: Software Development :: Libraries
Classifier: Programming Language :: Python :: 3
Classifier: License :: OSI Approved :: MIT License
Classifier: Operating System :: OS Independent
Requires-Python: >=3.6
Requires-Dist: graphene (<3,>=2.1.7)
Requires-Dist: graphene-django (<3,>=2.8)
Provides-Extra: dev
Requires-Dist: black (==19.10b0) ; extra == 'dev'
Requires-Dist: pytest (>=3.6.3) ; extra == 'dev'
Requires-Dist: pytest-django (>=3.3.2) ; extra == 'dev'
Provides-Extra: test
Requires-Dist: pytest (>=3.6.3) ; extra == 'test'
Requires-Dist: pytest-django (>=3.3.2) ; extra == 'test'
